setup.py
django_country/__init__.py
django_country/context_processors.py
django_country/geo.py
django_country/middleware.py
django_country/urls.py
django_country/views.py
django_country.egg-info/PKG-INFO
django_country.egg-info/SOURCES.txt
django_country.egg-info/dependency_links.txt
django_country.egg-info/not-zip-safe
django_country.egg-info/requires.txt
django_country.egg-info/top_level.txt