Metadata-Version: 1.0
Name: django-country
Version: 0.1.0
Summary: Provides Django middleware that detects a country the request came from.
Home-page: https://github.com/ColorGenomics/django-country
Author: Color Genomics, Inc.
Author-email: katsuya@getcolor.com
License: UNKNOWN
Platform: UNKNOWN
